{
  "slug": "discussion-topic",
  "name": "Discussion topic",
  "version": "1.0.0",
  "type": "type",
  "markers": [],
  "tags": [],
  "links": {},
  "active": true,
  "data": {
    "schema": {
      "type": "object",
      "properties": {
        "name": {
          "type": "string",
          "pattern": "^.*\\S.*$"
        },
        "tags": {
          "type": "array",
          "items": {
            "type": "string"
          },
          "$$formula": "AGGREGATE($events, 'tags')"
        },
        "data": {
          "type": "object",
          "properties": {
            "description": {
              "type": "string",
              "format": "markdown"
            },
            "type": {
              "type": "string",
              "default": "architecture",
              "enum": [
                "architecture",
                "product"
              ]
            },
            "status": {
              "title": "Status",
              "type": "string",
              "default": "open",
              "enum": [
                "open",
                "closed"
              ]
            }
          }
        }
      },
      "required": [
        "data"
      ]
    },
    "slices": [
      "properties.data.properties.status"
    ],
		"meta": {
			"relationships": [
				{
					"title": "Product improvement",
          "link": "discussion topic has attached product improvement",
					"type": "product-improvement"
				},
				{
					"title": "Specification",
          "link": "is source for",
					"type": "specification"
				},
				{
					"title": "Agenda",
          "link": "appears in",
					"type": "agenda"
				}
			]
		}
  },
  "requires": [],
  "capabilities": []
}
