{
  "slug": "view-all-messages",
  "name": "All chat messages",
  "type": "view",
  "tags": [],
  "links": [],
  "active": true,
  "data": {
    "allOf": [
      {
        "name": "Active cards",
        "schema": {
          "additionalProperties": true,
          "properties": {
            "active": {
              "const": true,
              "type": "boolean"
            }
          },
          "required": [
            "active"
          ],
          "type": "object"
        }
      },
      {
        "name": "user-generated-filter",
        "schema": {
          "anyOf": [
            {
              "description": "type is message",
              "properties": {
                "type": {
                  "const": "message"
                }
              },
              "required": [
                "type"
              ],
              "title": "is",
              "type": "object"
            }
          ],
          "type": "object"
        }
      }
    ],
    "lenses": [
      "lens-interleaved"
    ]
  }
}
